sfmergeutility/__init__.py
sfmergeutility/arm_document_generator.py
sfmergeutility/arm_parameter.py
sfmergeutility/constants.py
sfmergeutility/property_names.py
sfmergeutility/schema.py
sfmergeutility/settings.json
sfmergeutility/sf_merge_utility.py
sfmergeutility/sf_yaml_merge.py
sfmergeutility/sf_yaml_to_json.py
sfmergeutility/utility.py
sfmergeutility-0.1.5.dist-info/DESCRIPTION.rst
sfmergeutility-0.1.5.dist-info/METADATA
sfmergeutility-0.1.5.dist-info/RECORD
sfmergeutility-0.1.5.dist-info/WHEEL
sfmergeutility-0.1.5.dist-info/metadata.json
sfmergeutility-0.1.5.dist-info/top_level.txt
